cattqt/__init__.py
cattqt/cattqt.py
cattqt/chromecast.png
cattqt-4.0.dist-info/entry_points.txt
cattqt-4.0.dist-info/LICENSE
cattqt-4.0.dist-info/WHEEL
cattqt-4.0.dist-info/METADATA
cattqt-4.0.dist-info/RECORD
