Metadata-Version: 2.1
Name: cattqt
Version: 4.0
Summary: A control GUI for Chromecasts
Author-email: Scott Moreau <oreaus@gmail.com>
Requires-Python: >=3.0
Classifier: License :: OSI Approved :: GNU General Public License v3 or later (GPLv3+)
Project-URL: Source, https://github.com/soreau/catt-qt
